setu/__init__.py
setu/auth.py
setu/body.py
setu/contract.py
setu/deeplink.py
setu/endpoint.py
setu/serial.py
setu-2.0.0.dist-info/LICENSE
setu-2.0.0.dist-info/WHEEL
setu-2.0.0.dist-info/METADATA
setu-2.0.0.dist-info/RECORD
