Metadata-Version: 2.1
Name: setu
Version: 2.0.0
Summary: Python package to connect to Setu's UPI Deep Link APIs.
Home-page: https://github.com/SetuHQ/setu-python-sdk
License: MIT
Author: Naresh R
Author-email: ghostwriternr@gmail.com
Requires-Python: >=3.6.2,<4.0
Classifier: Development Status :: 5 - Production/Stable
Classifier: Intended Audience :: Developers
Classifier: License :: OSI Approved :: MIT License
Classifier: Natural Language :: English
Classifier: Programming Language :: Python :: 3
Classifier: Programming Language :: Python :: 3.10
Classifier: Programming Language :: Python :: 3.6
Classifier: Programming Language :: Python :: 3.7
Classifier: Programming Language :: Python :: 3.8
Classifier: Programming Language :: Python :: 3.9
Requires-Dist: Deprecated (>=1.2.13,<2.0.0)
Requires-Dist: PyJWT (>=2.4.0,<3.0.0)
Requires-Dist: marshmallow (>=3.14.1,<4.0.0)
Requires-Dist: marshmallow-oneofschema (>=3.0.1,<4.0.0)
Requires-Dist: requests (>=2.27.1,<3.0.0)
